api_spec_test/__init__.py
api_spec_test/drf.py
api_spec_test-0.1.0.dist-info/METADATA
api_spec_test-0.1.0.dist-info/WHEEL
api_spec_test-0.1.0.dist-info/top_level.txt
api_spec_test-0.1.0.dist-info/RECORD
