Metadata-Version: 2.1
Name: api-spec-test
Version: 0.1.0
Summary: A python REST API test library that tests based on API specification.
Home-page: https://github.com/heumlabs/api-spec-test
Author: Sangmin Kang
Author-email: ksmin@heumlabs.io
License: UNKNOWN
Platform: UNKNOWN
Classifier: Programming Language :: Python :: 3
Classifier: License :: OSI Approved :: MIT License
Classifier: Operating System :: OS Independent
Requires-Python: >=3.6
